gobtools/__init__.py
gobtools/utils/__init__.py
gobtools/utils/client.py
gobtools/utils/json.py
gobtools/weaver/__init__.py
gobtools/weaver/controller.py
gobtools-0.1.2.dist-info/METADATA
gobtools-0.1.2.dist-info/WHEEL
gobtools-0.1.2.dist-info/licenses/LICENSE
gobtools-0.1.2.dist-info/RECORD
