Metadata-Version: 2.3
Name: gobtools
Version: 0.1.2
Summary: Library to control and interact with the Goblin ecosystem.
Author-email: Hietan <hietan622@gmail.com>
License-File: LICENSE
Keywords: Goblin,Goblin Miner,Goblin Weaver
Requires-Python: >=3.8
Requires-Dist: requests>=2.32.3
